convizit/__init__.py
convizit/config.json
convizit/convizit.py
convizit-0.3.7.data/scripts/convizit_pkg
convizit-0.3.7.dist-info/LICENSE
convizit-0.3.7.dist-info/METADATA
convizit-0.3.7.dist-info/WHEEL
convizit-0.3.7.dist-info/top_level.txt
convizit-0.3.7.dist-info/RECORD
