Metadata-Version: 2.1
Name: convizit
Version: 0.3.7
Summary: Convizit database access package.
Home-page: https://github.com/Convizit/python-plugin
Author: Convizit
Author-email: convizit@gmail.com
License: UNKNOWN
Platform: UNKNOWN
Classifier: Programming Language :: Python :: 3
Classifier: License :: OSI Approved :: MIT License
Classifier: Operating System :: OS Independent
Requires-Dist: requests
